node_vm2/__init__.py
node_vm2/__pkginfo__.py
node_vm2/vm-server/index.js
node_vm2/vm-server/package-lock.json
node_vm2/vm-server/package.json
node_vm2/vm-server/node_modules/acorn/CHANGELOG.md
node_vm2/vm-server/node_modules/acorn/LICENSE
node_vm2/vm-server/node_modules/acorn/README.md
node_vm2/vm-server/node_modules/acorn/package.json
node_vm2/vm-server/node_modules/acorn/bin/acorn
node_vm2/vm-server/node_modules/acorn/dist/acorn.d.mts
node_vm2/vm-server/node_modules/acorn/dist/acorn.d.ts
node_vm2/vm-server/node_modules/acorn/dist/acorn.js
node_vm2/vm-server/node_modules/acorn/dist/acorn.mjs
node_vm2/vm-server/node_modules/acorn/dist/bin.js
node_vm2/vm-server/node_modules/acorn-walk/CHANGELOG.md
node_vm2/vm-server/node_modules/acorn-walk/LICENSE
node_vm2/vm-server/node_modules/acorn-walk/README.md
node_vm2/vm-server/node_modules/acorn-walk/package.json
node_vm2/vm-server/node_modules/acorn-walk/dist/walk.d.ts
node_vm2/vm-server/node_modules/acorn-walk/dist/walk.js
node_vm2/vm-server/node_modules/acorn-walk/dist/walk.mjs
node_vm2/vm-server/node_modules/vm2/CHANGELOG.md
node_vm2/vm-server/node_modules/vm2/LICENSE.md
node_vm2/vm-server/node_modules/vm2/README.md
node_vm2/vm-server/node_modules/vm2/index.d.ts
node_vm2/vm-server/node_modules/vm2/index.js
node_vm2/vm-server/node_modules/vm2/package.json
node_vm2/vm-server/node_modules/vm2/bin/vm2
node_vm2/vm-server/node_modules/vm2/lib/bridge.js
node_vm2/vm-server/node_modules/vm2/lib/builtin.js
node_vm2/vm-server/node_modules/vm2/lib/cli.js
node_vm2/vm-server/node_modules/vm2/lib/compiler.js
node_vm2/vm-server/node_modules/vm2/lib/events.js
node_vm2/vm-server/node_modules/vm2/lib/filesystem.js
node_vm2/vm-server/node_modules/vm2/lib/main.js
node_vm2/vm-server/node_modules/vm2/lib/nodevm.js
node_vm2/vm-server/node_modules/vm2/lib/resolver-compat.js
node_vm2/vm-server/node_modules/vm2/lib/resolver.js
node_vm2/vm-server/node_modules/vm2/lib/script.js
node_vm2/vm-server/node_modules/vm2/lib/setup-node-sandbox.js
node_vm2-0.4.7.dist-info/LICENSE
node_vm2-0.4.7.dist-info/METADATA
node_vm2-0.4.7.dist-info/WHEEL
node_vm2-0.4.7.dist-info/top_level.txt
node_vm2-0.4.7.dist-info/RECORD
