Metadata-Version: 2.1
Name: node-vm2
Version: 0.4.7
Summary: A binding to Node.js + vm2, helps you execute JavaScript safely.
Author-email: eight04 <eight04@gmail.com>
Project-URL: Homepage, https://github.com/eight04/node_vm2
Project-URL: Documentation, https://node-vm2.readthedocs.io/en/latest/?badge=latest
Project-URL: Bug Tracker, https://github.com/eight04/node_vm2/issues
Keywords: node,js,sandbox,execute,javascript
Classifier: Development Status :: 4 - Beta
Classifier: Environment :: Console
Classifier: Environment :: Win32 (MS Windows)
Classifier: Intended Audience :: Developers
Classifier: License :: OSI Approved :: MIT License
Classifier: Natural Language :: Chinese (Traditional)
Classifier: Operating System :: Microsoft :: Windows :: Windows 7
Classifier: Programming Language :: Python :: 3.6
Classifier: Programming Language :: JavaScript
Classifier: Topic :: Software Development :: Libraries
Requires-Python: >=3.7
License-File: LICENSE
